{
  "cached_at": "2025-12-03T06:41:30.683941+00:00",
  "data": {
    "url": "https://www.businessinsider.com/china-embodied-intelligence-major-universities-robotics-talent-ai-zhejiang-2025-12",
    "title": "China's top universities plan to roll out 'embodied intelligence' majors to fuel Beijing's robotics push",
    "description": "Seven Chinese universities plan to launch an \"embodied intelligence\" major as Beijing races to build a pipeline of robotics and AI talent.",
    "image": "https://i.insider.com/692fb4247ecd1d1da662d15e?width=1200&format=jpeg",
    "favicon": "https://www.businessinsider.com/public/assets/BI/US/favicons/apple-touch-icon-180x180.png?v=2025-05",
    "site_name": "Business Insider",
    "author": null,
    "keywords": null
  }
}