{
  "cached_at": "2025-12-02T01:22:07.411831+00:00",
  "data": {
    "url": "https://www.cnbc.com/2025/12/02/the-ai-trade-with-a-lot-of-upside-not-much-downside-strategist-.html",
    "title": "Strategist reveals an 'asymmetric AI' trade: 'A lot of\u00a0upside\u00a0without much downside'",
    "description": "Speaking with CNBC's \"Squawk Box Europe,\" Schroders'\u00a0head of multi-asset income\u00a0Dorian Carrell revealed his advice to clients.",
    "image": "https://image.cnbcfm.com/api/v1/image/108194138-1756981037270-gettyimages-2214393202-avdtnmymay25lot2jj.jpeg?v=1761941786&w=1920&h=1080",
    "favicon": "https://sc.cnbcfm.com/applications/cnbc.com/staticcontent/img/favicon.ico",
    "site_name": "CNBC",
    "author": "Tasmin Lockwood",
    "keywords": "Breaking News: Markets,Markets,Alphabet Class A,Meta Platforms Inc,Fresh Vine Wine Inc,business news"
  }
}