{
  "subreddit": "Bitcoin",
  "posts": [
    {
      "title": "Just a good reminder for all off you guys...",
      "author": "Glittering_Lie3436",
      "url": "https://www.reddit.com/r/Bitcoin/comments/1pf1bim/just_a_good_reminder_for_all_off_you_guys/",
      "published": 1764956163.0,
      "thumbnail": "https://external-preview.redd.it/a202MDZiYnQ4ZjVnMUSPKdIcvBzva7eSGpmSwO9NqH9TM8lUE59xer7LTmBJ.png?width=640&crop=smart&auto=webp&s=f801ae10d9a64b199f4fff9e9f3357d3d9b95613",
      "external_url": null,
      "site_name": null,
      "favicon": null,
      "description": null
    },
    {
      "title": "The most expensive mistake is always selling your BTC",
      "author": "Cryptomuscom",
      "url": "https://www.reddit.com/r/Bitcoin/comments/1peu9r7/the_most_expensive_mistake_is_always_selling_your/",
      "published": 1764939091.0,
      "thumbnail": "https://preview.redd.it/avilez6lsd5g1.jpeg?width=640&crop=smart&auto=webp&s=c034100fb9483dc6c5b77ab48546b448a77ad78a",
      "external_url": null,
      "site_name": null,
      "favicon": null,
      "description": null
    },
    {
      "title": "POV: You\u2019re the only one who actually got a deal on Black Friday.",
      "author": "North_Appointment410",
      "url": "https://www.reddit.com/r/Bitcoin/comments/1pew8t1/pov_youre_the_only_one_who_actually_got_a_deal_on/",
      "published": 1764944343.0,
      "thumbnail": "https://preview.redd.it/moq7h87n9e5g1.jpeg?width=640&crop=smart&auto=webp&s=0e60ba15460d93cc640ac30a3f19299e2e4eb337",
      "external_url": null,
      "site_name": null,
      "favicon": null,
      "description": null
    },
    {
      "title": "Got to 0.1 !!",
      "author": "retiamus",
      "url": "https://www.reddit.com/r/Bitcoin/comments/1pf2id0/got_to_01/",
      "published": 1764958848.0,
      "thumbnail": "https://preview.redd.it/oicfcaysgf5g1.jpeg?width=640&crop=smart&auto=webp&s=434bad93d490e911ba728f571aa174cfa4f88305",
      "external_url": null,
      "site_name": null,
      "favicon": null,
      "description": null
    },
    {
      "title": "I just get 100$ of btc",
      "author": "leanypv",
      "url": "https://www.reddit.com/r/Bitcoin/comments/1pf0gru/i_just_get_100_of_btc/",
      "published": 1764954206.0,
      "thumbnail": null,
      "external_url": null,
      "site_name": null,
      "favicon": null,
      "description": "Hi I\u2019m new to this. I don\u2019t have a lot of money to put into it but wanted to start with 100. It\u2019s ok ?"
    },
    {
      "title": "The Struggle\u2026.",
      "author": "Frostdotco",
      "url": "https://www.reddit.com/r/Bitcoin/comments/1peipkt/the_struggle/",
      "published": 1764899977.0,
      "thumbnail": "https://preview.redd.it/uec2picrla5g1.jpeg?width=320&crop=smart&auto=webp&s=dbea9253f1c94507af8133b82e78aa0018c84d3b",
      "external_url": null,
      "site_name": null,
      "favicon": null,
      "description": "Im only up 3000% now"
    },
    {
      "title": "Bitcoin can fix this?",
      "author": "Leading_Confection32",
      "url": "https://www.reddit.com/r/Bitcoin/comments/1pekul0/bitcoin_can_fix_this/",
      "published": 1764906095.0,
      "thumbnail": "https://preview.redd.it/1xkyvjby3b5g1.jpeg?width=640&crop=smart&auto=webp&s=f969cef7a6910f3f7ecd5986568cfdd495a7e304",
      "external_url": null,
      "site_name": null,
      "favicon": null,
      "description": null
    },
    {
      "title": "What stops someone from taking on as much credit card debt as they can, using all the money to buy Bitcoin, then declaring bankruptcy to absolve the debt and keep the profits?",
      "author": "TerminatedPotato",
      "url": "https://www.reddit.com/r/Bitcoin/comments/1pf19nt/what_stops_someone_from_taking_on_as_much_credit/",
      "published": 1764956046.0,
      "thumbnail": null,
      "external_url": null,
      "site_name": null,
      "favicon": null,
      "description": "It can't just be as simple as that, can it? Maybe it is but I just know I would fuck it up. Obviously that can't be sustainable as a financial system but that's how it all seems to work outside of the Bitcoin system."
    },
    {
      "title": "from \"the big print\" by Lawrence Lepard. I think we are not bullish enough",
      "author": "DryMyBottom",
      "url": "https://www.reddit.com/r/Bitcoin/comments/1pf1m8e/from_the_big_print_by_lawrence_lepard_i_think_we/",
      "published": 1764956841.0,
      "thumbnail": "https://preview.redd.it/rhkrdubuaf5g1.jpeg?width=640&crop=smart&auto=webp&s=fe5d7855b0d3399613f0a2e745e33bb68177fa5d",
      "external_url": null,
      "site_name": null,
      "favicon": null,
      "description": "... not in the slightest"
    },
    {
      "title": "Senators buying the dip on BTC",
      "author": "anonbull8",
      "url": "https://www.reddit.com/r/Bitcoin/comments/1pem50a/senators_buying_the_dip_on_btc/",
      "published": 1764910044.0,
      "thumbnail": "https://preview.redd.it/01p34j1pfb5g1.jpeg?width=640&crop=smart&auto=webp&s=9cc877d213b2a5312675f66bc52c9e878eb27a6a",
      "external_url": null,
      "site_name": null,
      "favicon": null,
      "description": "Looks like the Senator from Pennsylvania is buying the dip on Bitcoin by buying into IBIT\u2026 and so is Marjorie Greene \ud83e\udee3"
    }
  ],
  "fetched_at": "2025-12-05T19:14:03.882332+00:00"
}