{
  "title": "YouTube Videos",
  "query": "ethereum",
  "order": "relevance",
  "videos": [
    {
      "video_id": "X_bq7p7kr4g",
      "title": "Ethereum 2026 Prediction (Not What you Think!)",
      "description": "Deezy checks the data surrounding the Fed's recent pivot. Quantitative tightening is over and the Fed balance sheet will soon rise.",
      "channel_name": "Discover Crypto",
      "channel_id": "UCjemQfjaXAzA-95RKoy9n_g",
      "thumbnail": "https://i.ytimg.com/vi/X_bq7p7kr4g/hqdefault.jpg",
      "published_at": 1764720045.0,
      "url": "https://www.youtube.com/watch?v=X_bq7p7kr4g",
      "duration": "6:35",
      "view_count": 1872,
      "view_count_display": "2K",
      "like_count": 147,
      "like_count_display": "147",
      "comment_count": 6,
      "comment_count_display": "6",
      "channel_avatar": "https://yt3.ggpht.com/ByeOVnzg4NGjB901wnWg3mmKPG6_kUXGqOLhrGs7-adpkZ3YCUsNcvTwDEcV_XOT-i7HOIla=s88-c-k-c0x00ffffff-no-rj"
    },
    {
      "video_id": "_N-xXeC_YGk",
      "title": "Tom Lee: \u201cEveryone Is Wrong About What\u2019s Coming Next for Ethereum\u201d [New 2026 Prediction]",
      "description": "My FREE Daily 5-Min Crypto Newsletter: https://www.cryptonutshell.com/subscribe \u2b95 Cold Storage Wallet: ...",
      "channel_name": "Crypto Nutshell",
      "channel_id": "UC1owqQFqzvOP5hEWBINpDWg",
      "thumbnail": "https://i.ytimg.com/vi/_N-xXeC_YGk/hqdefault.jpg",
      "published_at": 1764688509.0,
      "url": "https://www.youtube.com/watch?v=_N-xXeC_YGk",
      "duration": "21:08",
      "view_count": 7862,
      "view_count_display": "8K",
      "like_count": 310,
      "like_count_display": "310",
      "comment_count": 45,
      "comment_count_display": "45",
      "channel_avatar": "https://yt3.ggpht.com/7UgX-CDy0-pAMViF_9l1LUUKWaET5EJWCkjTkSjdnkKhT6vgxEUjDhgZ7QXIiG2HIMxFxCNTuQ=s88-c-k-c0x00ffffff-no-rj"
    },
    {
      "video_id": "NYMpjTHlS4Y",
      "title": "Ethereum Elliott Wave Update \u2013 Key Resistance Levels Ahead",
      "description": "This video provides a professional Elliott Wave and technical analysis of Ethereum (ETH), focusing on market structure, major ...",
      "channel_name": "More Crypto Online",
      "channel_id": "UCngIhBkikUe6e7tZTjpKK7Q",
      "thumbnail": "https://i.ytimg.com/vi/NYMpjTHlS4Y/hqdefault.jpg",
      "published_at": 1764727067.0,
      "url": "https://www.youtube.com/watch?v=NYMpjTHlS4Y",
      "duration": "6:54",
      "view_count": 369,
      "view_count_display": "369",
      "like_count": 36,
      "like_count_display": "36",
      "comment_count": 3,
      "comment_count_display": "3",
      "channel_avatar": "https://yt3.ggpht.com/lKp1RAXR6bdVGybEYj2J4_y6FLPK5ysaLw7-BHliSb2HGYYaQXj5IXPlFPtESnWy6HqQpycD=s88-c-k-c0x00ffffff-no-rj"
    },
    {
      "video_id": "oX7lLD3e3h4",
      "title": "Fed Wants Ethereum to Win! Is $BMNR the Ultimate Play? EXPLAINED",
      "description": "Does the Federal Reserve want Ethereum to win? In this video, we analyze the massive regulatory shift happening in the U.S., ...",
      "channel_name": "CryptoStock Lab",
      "channel_id": "UCuM_3w5yUBcc13Muco7eQ_w",
      "thumbnail": "https://i.ytimg.com/vi/oX7lLD3e3h4/hqdefault.jpg",
      "published_at": 1764693910.0,
      "url": "https://www.youtube.com/watch?v=oX7lLD3e3h4",
      "duration": "7:35",
      "view_count": 1798,
      "view_count_display": "2K",
      "like_count": 70,
      "like_count_display": "70",
      "comment_count": 34,
      "comment_count_display": "34",
      "channel_avatar": "https://yt3.ggpht.com/2CSupsn2sbN9t92UjcbwF3PB1JlSWZhXYMHVV8lI_WLq7GFS73It67lIG86FNNTYQclwjhpRUg=s88-c-k-c0x00ffffff-no-rj"
    },
    {
      "video_id": "L6YGBLPy2Jw",
      "title": "Ethereum Elliott Wave Update \u2013 Key Resistance Levels Ahead",
      "description": "This video provides a professional Elliott Wave and technical analysis of Ethereum (ETH), focusing on market structure, major ...",
      "channel_name": "More Crypto Online",
      "channel_id": "UCngIhBkikUe6e7tZTjpKK7Q",
      "thumbnail": "https://i.ytimg.com/vi/L6YGBLPy2Jw/hqdefault.jpg",
      "published_at": 1764683629.0,
      "url": "https://www.youtube.com/watch?v=L6YGBLPy2Jw",
      "duration": "4:45",
      "view_count": 2897,
      "view_count_display": "3K",
      "like_count": 181,
      "like_count_display": "181",
      "comment_count": 6,
      "comment_count_display": "6",
      "channel_avatar": "https://yt3.ggpht.com/lKp1RAXR6bdVGybEYj2J4_y6FLPK5ysaLw7-BHliSb2HGYYaQXj5IXPlFPtESnWy6HqQpycD=s88-c-k-c0x00ffffff-no-rj"
    },
    {
      "video_id": "A7m363aon0E",
      "title": "BITCOIN &amp; ALTCOINS FLIPPED: Everyone is WRONG!!!! - Bitcoin News Today, Ethereum &amp; Altcoins",
      "description": "BITCOIN & ALTCOINS FLIPPED: Everyone is WRONG!!!! - Bitcoin News Today, Ethereum & Altcoins *Pionex* ...",
      "channel_name": "Crypto World",
      "channel_id": "UCgY66N1YS_G9lYMvCQko6yw",
      "thumbnail": "https://i.ytimg.com/vi/A7m363aon0E/hqdefault.jpg",
      "published_at": 1764691515.0,
      "url": "https://www.youtube.com/watch?v=A7m363aon0E",
      "duration": "19:37",
      "view_count": 11104,
      "view_count_display": "11K",
      "like_count": 416,
      "like_count_display": "416",
      "comment_count": 85,
      "comment_count_display": "85",
      "channel_avatar": "https://yt3.ggpht.com/AYWV5uYiaehsmX977c3P15wgS0j82ICzgVwq3zm07czXnwmafuSTnzEB-C6rJk9RZ1U3gv2eGg=s88-c-k-c0x00ffffff-no-rj"
    },
    {
      "video_id": "xmC-bCgpxZs",
      "title": "Bitcoin &amp; Ethereum Price Prediction Now | Crypto Analysis &amp; Market Forecast",
      "description": "Get daily Bitcoin & Crypto signals in our VIP Discord via Patreon https://www.patreon.com/ThomasBoleto/membership ...",
      "channel_name": "Thomas Boleto \u2013 Bitcoin Insights",
      "channel_id": "UCdJumIG5zW_KnM5cylplt-Q",
      "thumbnail": "https://i.ytimg.com/vi/xmC-bCgpxZs/hqdefault.jpg",
      "published_at": 1764727033.0,
      "url": "https://www.youtube.com/watch?v=xmC-bCgpxZs",
      "duration": "14:39",
      "view_count": 50,
      "view_count_display": "50",
      "like_count": 14,
      "like_count_display": "14",
      "comment_count": 2,
      "comment_count_display": "2",
      "channel_avatar": "https://yt3.ggpht.com/0R9e7gQ4TzkqMpoCNwRnE0ka8f0dm8dRD1EqDW7obmfs5B31cVsC4tuyp97UaWeMxUbBysWv=s88-c-k-c0x00ffffff-no-rj"
    },
    {
      "video_id": "C7He2l_U5Jo",
      "title": "\ud83d\udea8 BTC &amp; ETH: SUPER URGENT UPDATE!!! TRADERS BEWARE!!!!!!!!!!!",
      "description": "This new data has huge implications for bitcoin, ethereum and the rest of crypto! Be experemely careful now! Here is what to ...",
      "channel_name": "Thomas Kralow",
      "channel_id": "UCBhORXMwPfJtNtsZcUJHO6w",
      "thumbnail": "https://i.ytimg.com/vi/C7He2l_U5Jo/hqdefault.jpg",
      "published_at": 1764590298.0,
      "url": "https://www.youtube.com/watch?v=C7He2l_U5Jo",
      "duration": "11:06",
      "view_count": 34290,
      "view_count_display": "34K",
      "like_count": 2178,
      "like_count_display": "2K",
      "comment_count": 69,
      "comment_count_display": "69",
      "channel_avatar": "https://yt3.ggpht.com/T6eylFzRoWiLFQnmessN-5t4QwDWnUobHhHyVJv92zGafMJHV8X4tbGxZU2iwgbzpc0Ec-BJPfY=s88-c-k-c0x00ffffff-no-rj"
    },
    {
      "video_id": "t-bwcTZ66zo",
      "title": "Ethereum Fusaka Upgrade This Week!\ud83d\udd25BEAST MODE Coming \ud83d\udea8Justin Drake ETH Foundation",
      "description": "Valuable upgrades to the Ethereum network will be rolled out on December 3, 2025, Fusaka mainnet upgrade. This specific ...",
      "channel_name": "Paul Barron Network",
      "channel_id": "UC4VPa7EOvObpyCRI4YKRQRw",
      "thumbnail": "https://i.ytimg.com/vi/t-bwcTZ66zo/hqdefault.jpg",
      "published_at": 1764621073.0,
      "url": "https://www.youtube.com/watch?v=t-bwcTZ66zo",
      "duration": "23:58",
      "view_count": 21571,
      "view_count_display": "22K",
      "like_count": 938,
      "like_count_display": "938",
      "comment_count": 78,
      "comment_count_display": "78",
      "channel_avatar": "https://yt3.ggpht.com/cjXiGAgHvgSASNMfzMHW7ZNU9dTAhof0VnmSh04y7dv2muMDR-JBuCKg3sI_QBLn_Bp2QGYY=s88-c-k-c0x00ffffff-no-rj"
    },
    {
      "video_id": "pqIaBF5eqYk",
      "title": "BITCOIN: It\u2019s All a Trap! (prepare now) - BTC, ETH Price Prediction Today",
      "description": "Want a free $30000 bonus + $20 just for signing up? Go here: ...",
      "channel_name": "BitcoinHyper",
      "channel_id": "UCVEQTVuaFpcatHDhKIyhZmQ",
      "thumbnail": "https://i.ytimg.com/vi/pqIaBF5eqYk/hqdefault.jpg",
      "published_at": 1764674145.0,
      "url": "https://www.youtube.com/watch?v=pqIaBF5eqYk",
      "duration": "13:06",
      "view_count": 11661,
      "view_count_display": "12K",
      "like_count": 602,
      "like_count_display": "602",
      "comment_count": 47,
      "comment_count_display": "47",
      "channel_avatar": "https://yt3.ggpht.com/ytc/AIdro_kUbyHsSn19A5ttEyxdPN2qQIYWXp_F9nMtydt2PBG4MA=s88-c-k-c0x00ffffff-no-rj"
    }
  ],
  "fetched_at": "2025-12-03T02:53:16.005840+00:00"
}